torchmetrics/__about__.py
torchmetrics/__init__.py
torchmetrics/aggregation.py
torchmetrics/collections.py
torchmetrics/metric.py
torchmetrics/py.typed
torchmetrics/audio/__init__.py
torchmetrics/audio/_deprecated.py
torchmetrics/audio/dnsmos.py
torchmetrics/audio/nisqa.py
torchmetrics/audio/pesq.py
torchmetrics/audio/pit.py
torchmetrics/audio/sdr.py
torchmetrics/audio/snr.py
torchmetrics/audio/srmr.py
torchmetrics/audio/stoi.py
torchmetrics/classification/__init__.py
torchmetrics/classification/accuracy.py
torchmetrics/classification/auroc.py
torchmetrics/classification/average_precision.py
torchmetrics/classification/base.py
torchmetrics/classification/calibration_error.py
torchmetrics/classification/cohen_kappa.py
torchmetrics/classification/confusion_matrix.py
torchmetrics/classification/eer.py
torchmetrics/classification/exact_match.py
torchmetrics/classification/f_beta.py
torchmetrics/classification/group_fairness.py
torchmetrics/classification/hamming.py
torchmetrics/classification/hinge.py
torchmetrics/classification/jaccard.py
torchmetrics/classification/logauc.py
torchmetrics/classification/matthews_corrcoef.py
torchmetrics/classification/negative_predictive_value.py
torchmetrics/classification/precision_fixed_recall.py
torchmetrics/classification/precision_recall.py
torchmetrics/classification/precision_recall_curve.py
torchmetrics/classification/ranking.py
torchmetrics/classification/recall_fixed_precision.py
torchmetrics/classification/roc.py
torchmetrics/classification/sensitivity_specificity.py
torchmetrics/classification/specificity.py
torchmetrics/classification/specificity_sensitivity.py
torchmetrics/classification/stat_scores.py
torchmetrics/clustering/__init__.py
torchmetrics/clustering/adjusted_mutual_info_score.py
torchmetrics/clustering/adjusted_rand_score.py
torchmetrics/clustering/calinski_harabasz_score.py
torchmetrics/clustering/cluster_accuracy.py
torchmetrics/clustering/davies_bouldin_score.py
torchmetrics/clustering/dunn_index.py
torchmetrics-1.7.0.dist-info/licenses/LICENSE
torchmetrics-1.7.0.dist-info/METADATA
torchmetrics-1.7.0.dist-info/WHEEL
torchmetrics-1.7.0.dist-info/top_level.txt
torchmetrics-1.7.0.dist-info/RECORD
