Metadata-Version: 2.4
Name: torchmetrics
Version: 1.7.0
Summary: PyTorch native Metrics
Home-page: https://github.com/Lightning-AI/torchmetrics
Download-URL: https://github.com/Lightning-AI/torchmetrics/archive/master.zip
Author: Lightning-AI et al.
Author-email: name@pytorchlightning.ai
License: Apache-2.0
Project-URL: Bug Tracker, https://github.com/Lightning-AI/torchmetrics/issues
Project-URL: Documentation, https://torchmetrics.rtfd.io/en/latest/
Project-URL: Source Code, https://github.com/Lightning-AI/torchmetrics
Keywords: deep learning,machine learning,pytorch,metrics,AI
Classifier: Environment :: Console
Classifier: Natural Language :: English
Classifier: Development Status :: 5 - Production/Stable
Classifier: Intended Audience :: Developers
Classifier: Topic :: Scientific/Engineering :: Artificial Intelligence
Classifier: Topic :: Scientific/Engineering :: Image Recognition
Classifier: Topic :: Scientific/Engineering :: Information Analysis
Classifier: License :: OSI Approved :: Apache Software License
Classifier: Operating System :: OS Independent
Classifier: Programming Language :: Python :: 3
Classifier: Programming Language :: Python :: 3.8
Classifier: Programming Language :: Python :: 3.9
Classifier: Programming Language :: Python :: 3.10
Classifier: Programming Language :: Python :: 3.11
Classifier: Programming Language :: Python :: 3.12
Requires-Python: >=3.9
License-File: LICENSE
Requires-Dist: numpy>1.20.0
Requires-Dist: packaging>17.1
Requires-Dist: torch>=2.0.0
Requires-Dist: lightning-utilities>=0.8.0
Provides-Extra: audio
Requires-Dist: requests>=2.19.0; extra == "audio"
Requires-Dist: onnxruntime>=1.12.0; extra == "audio"
Requires-Dist: torchaudio>=2.0.1; extra == "audio"
Requires-Dist: pystoi>=0.4.0; extra == "audio"
Requires-Dist: gammatone>=1.0.0; extra == "audio"
Requires-Dist: pesq>=0.0.4; extra == "audio"
Requires-Dist: librosa>=0.10.0; extra == "audio"
Provides-Extra: clustering
Requires-Dist: torch_linear_assignment>=0.0.2; extra == "clustering"
Provides-Extra: debug
Provides-Extra: detection
Requires-Dist: torchvision>=0.15.1; extra == "detection"
Requires-Dist: pycocotools>2.0.0; extra == "detection"
Provides-Extra: image
Requires-Dist: torch-fidelity<=0.4.0; extra == "image"
Requires-Dist: torchvision>=0.15.1; extra == "image"
Requires-Dist: scipy>1.0.0; extra == "image"
Provides-Extra: integrate
Provides-Extra: multimodal
Requires-Dist: piq<=0.8.0; extra == "multimodal"
Requires-Dist: timm>=0.9.0; extra == "multimodal"
Requires-Dist: transformers>=4.42.3; extra == "multimodal"
Requires-Dist: einops>=0.7.0; extra == "multimodal"
Provides-Extra: text
Requires-Dist: transformers>4.4.0; extra == "text"
Requires-Dist: sentencepiece>=0.2.0; extra == "text"
Requires-Dist: nltk>3.8.1; extra == "text"
Requires-Dist: mecab-python3>=1.0.6; extra == "text"
Requires-Dist: tqdm<4.68.0; extra == "text"
Requires-Dist: regex>=2021.9.24; extra == "text"
Requires-Dist: ipadic>=1.0.0; extra == "text"
Provides-Extra: typing
Requires-Dist: types-setuptools; extra == "typing"
Requires-Dist: types-PyYAML; extra == "typing"
Requires-Dist: mypy==1.15.0; extra == "typing"
Requires-Dist: types-six; extra == "typing"
Requires-Dist: types-requests; extra == "typing"
Requires-Dist: types-emoji; extra == "typing"
Requires-Dist: torch==2.6.0; extra == "typing"
Requires-Dist: types-tabulate; extra == "typing"
Requires-Dist: types-protobuf; extra == "typing"
Provides-Extra: visual
Requires-Dist: SciencePlots>=2.0.0; extra == "visual"
Requires-Dist: matplotlib>=3.6.0; extra == "visual"
Provides-Extra: all
Requires-Dist: requests>=2.19.0; extra == "all"
Requires-Dist: onnxruntime>=1.12.0; extra == "all"
Requires-Dist: torchaudio>=2.0.1; extra == "all"
Requires-Dist: pystoi>=0.4.0; extra == "all"
Requires-Dist: gammatone>=1.0.0; extra == "all"
Requires-Dist: pesq>=0.0.4; extra == "all"
Requires-Dist: librosa>=0.10.0; extra == "all"
Requires-Dist: torch_linear_assignment>=0.0.2; extra == "all"
Requires-Dist: torchvision>=0.15.1; extra == "all"
Requires-Dist: pycocotools>2.0.0; extra == "all"
Requires-Dist: torch-fidelity<=0.4.0; extra == "all"
Requires-Dist: torchvision>=0.15.1; extra == "all"
Requires-Dist: scipy>1.0.0; extra == "all"
Requires-Dist: piq<=0.8.0; extra == "all"
Requires-Dist: timm>=0.9.0; extra == "all"
Requires-Dist: transformers>=4.42.3; extra == "all"
Requires-Dist: einops>=0.7.0; extra == "all"
Requires-Dist: transformers>4.4.0; extra == "all"
Requires-Dist: sentencepiece>=0.2.0; extra == "all"
Requires-Dist: nltk>3.8.1; extra == "all"
Requires-Dist: mecab-python3>=1.0.6; extra == "all"
Requires-Dist: tqdm<4.68.0; extra == "all"
Requires-Dist: regex>=2021.9.24; extra == "all"
Requires-Dist: ipadic>=1.0.0; extra == "all"
Requires-Dist: types-setuptools; extra == "all"
Requires-Dist: types-PyYAML; extra == "all"
Requires-Dist: mypy==1.15.0; extra == "all"
Requires-Dist: types-six; extra == "all"
Requires-Dist: types-requests; extra == "all"
Requires-Dist: types-emoji; extra == "all"
Requires-Dist: torch==2.6.0; extra == "all"
Requires-Dist: types-tabulate; extra == "all"
Requires-Dist: types-protobuf; extra == "all"
Requires-Dist: SciencePlots>=2.0.0; extra == "all"
Requires-Dist: matplotlib>=3.6.0; extra == "all"
Provides-Extra: dev
Requires-Dist: requests>=2.19.0; extra == "dev"
Requires-Dist: onnxruntime>=1.12.0; extra == "dev"
Requires-Dist: torchaudio>=2.0.1; extra == "dev"
Requires-Dist: pystoi>=0.4.0; extra == "dev"
Requires-Dist: gammatone>=1.0.0; extra == "dev"
Requires-Dist: pesq>=0.0.4; extra == "dev"
Requires-Dist: librosa>=0.10.0; extra == "dev"
Requires-Dist: torch_linear_assignment>=0.0.2; extra == "dev"
Requires-Dist: torchvision>=0.15.1; extra == "dev"
Requires-Dist: pycocotools>2.0.0; extra == "dev"
Requires-Dist: torch-fidelity<=0.4.0; extra == "dev"
Requires-Dist: torchvision>=0.15.1; extra == "dev"
Requires-Dist: scipy>1.0.0; extra == "dev"
Requires-Dist: piq<=0.8.0; extra == "dev"
Requires-Dist: timm>=0.9.0; extra == "dev"
Requires-Dist: transformers>=4.42.3; extra == "dev"
Requires-Dist: einops>=0.7.0; extra == "dev"
Requires-Dist: transformers>4.4.0; extra == "dev"
Requires-Dist: sentencepiece>=0.2.0; extra == "dev"
Requires-Dist: nltk>3.8.1; extra == "dev"
Requires-Dist: mecab-python3>=1.0.6; extra == "dev"
Requires-Dist: tqdm<4.68.0; extra == "dev"
Requires-Dist: regex>=2021.9.24; extra == "dev"
Requires-Dist: ipadic>=1.0.0; extra == "dev"
Requires-Dist: types-setuptools; extra == "dev"
Requires-Dist: types-PyYAML; extra == "dev"
Requires-Dist: mypy==1.15.0; extra == "dev"
Requires-Dist: types-six; extra == "dev"
Requires-Dist: types-requests; extra == "dev"
Requires-Dist: types-emoji; extra == "dev"
Requires-Dist: torch==2.6.0; extra == "dev"
Requires-Dist: types-tabulate; extra == "dev"
Requires-Dist: types-protobuf; extra == "dev"
Requires-Dist: SciencePlots>=2.0.0; extra == "dev"
Requires-Dist: matplotlib>=3.6.0; extra == "dev"
Requires-Dist: fairlearn; extra == "dev"
Requires-Dist: dython==0.7.9; extra == "dev"
Requires-Dist: mecab-ko-dic>=1.0.0; python_version < "3.12" and extra == "dev"
Requires-Dist: PyTDC==0.4.1; python_version < "3.12" and extra == "dev"
Requires-Dist: torch_complex<0.5.0; extra == "dev"
Requires-Dist: permetrics==2.0.0; extra == "dev"
Requires-Dist: pandas>1.4.0; extra == "dev"
Requires-Dist: pytorch-msssim==1.0.0; extra == "dev"
Requires-Dist: jiwer>=2.3.0; extra == "dev"
Requires-Dist: mecab-ko<1.1.0,>=1.0.0; python_version < "3.12" and extra == "dev"
Requires-Dist: statsmodels>0.13.5; extra == "dev"
Requires-Dist: huggingface-hub<0.30; extra == "dev"
Requires-Dist: aeon>=1.0.0; python_version > "3.10" and extra == "dev"
Requires-Dist: bert_score==0.3.13; extra == "dev"
Requires-Dist: numpy<2.3.0; extra == "dev"
Requires-Dist: scipy>1.0.0; extra == "dev"
Requires-Dist: monai==1.4.0; extra == "dev"
Requires-Dist: sewar>=0.4.4; extra == "dev"
Requires-Dist: fast-bss-eval>=0.1.0; extra == "dev"
Requires-Dist: netcal>1.0.0; extra == "dev"
Requires-Dist: kornia>=0.6.7; extra == "dev"
Requires-Dist: sacrebleu>=2.3.0; extra == "dev"
Requires-Dist: rouge-score>0.1.0; extra == "dev"
Requires-Dist: mir-eval>=0.6; extra == "dev"
Requires-Dist: lpips<=0.1.4; extra == "dev"
Requires-Dist: dists-pytorch==0.1; extra == "dev"
Requires-Dist: scikit-image>=0.19.0; extra == "dev"
Requires-Dist: faster-coco-eval>=1.6.3; extra == "dev"
Dynamic: author
Dynamic: author-email
Dynamic: classifier
Dynamic: description
Dynamic: description-content-type
Dynamic: download-url
Dynamic: home-page
Dynamic: keywords
Dynamic: license
Dynamic: license-file
Dynamic: project-url
Dynamic: provides-extra
Dynamic: requires-dist
Dynamic: requires-python
Dynamic: summary
